Metadata-Version: 1.0
Name: reqtxtupd8
Version: 1.1
Summary: Writes your package list to requirements.txt
Home-page: https://github.com/edmamerto/reqtxtupd8
Author: Edgar Mamerto
Author-email: edmamerto@gmail.com
License: UNKNOWN
Platform: UNKNOWN
